fms_acceleration_aadp/__init__.py
fms_acceleration_aadp/aadp_utils.py
fms_acceleration_aadp/flash_attn.py
fms_acceleration_aadp/framework_plugin_multipack.py
fms_acceleration_aadp/framework_plugin_padding_free.py
fms_acceleration_aadp/multipack_sampler.py
fms_acceleration_aadp-0.2.1.dist-info/METADATA
fms_acceleration_aadp-0.2.1.dist-info/WHEEL
fms_acceleration_aadp-0.2.1.dist-info/RECORD
