Metadata-Version: 2.4
Name: fms-acceleration-aadp
Version: 0.2.1
Summary: FMS Acceleration Plugin for Attention and Distributed Packing Optimizations
Author-email: Fabian Lim <flim@sg.ibm.com>, Aaron Chew <aaron.chew1@ibm.com>
License: Apache-2.0
Keywords: acceleration,fms-hf-tuning,multipack,padding-free
Classifier: Development Status :: 4 - Beta
Classifier: License :: OSI Approved :: Apache Software License
Classifier: Programming Language :: Python :: 3
Classifier: Programming Language :: Python :: 3.9
Classifier: Programming Language :: Python :: 3.10
Classifier: Programming Language :: Python :: 3.11
Requires-Python: ~=3.9
Requires-Dist: numba
Requires-Dist: trl<0.20.0,>=0.19.1
